pandas_shortcuts/__init__.py
pandas_shortcuts/dataframe_api.py
pandas_shortcuts/series_api.py
pandas_shortcuts/top_level_api.py
pandas_shortcuts/methods/__init__.py
pandas_shortcuts/methods/methods.py
pandas_shortcuts-0.1.dist-info/LICENSE
pandas_shortcuts-0.1.dist-info/METADATA
pandas_shortcuts-0.1.dist-info/WHEEL
pandas_shortcuts-0.1.dist-info/top_level.txt
pandas_shortcuts-0.1.dist-info/RECORD
