Metadata-Version: 2.1
Name: pandas_shortcuts
Version: 0.1
Summary: Why even wait for autocompletion when you can use `pandas_shortcuts`?
Author-email: BaoGiang HoangVu <hoangvubaogiang@gmail.com>, lpun-majessica <nhi.lpu1205@gmail.com>
License: MIT License
Project-URL: Bug Reports, https://github.com/baogianghoangvu/pandas-shortcuts/issues
Project-URL: Source, https://github.com/baogianghoangvu/pandas-shortcuts
Keywords: shortcut,pandas
Classifier: Development Status :: 3 - Alpha
Classifier: Intended Audience :: Science/Research
Classifier: Natural Language :: English
Classifier: Programming Language :: Python :: 3
Classifier: Operating System :: OS Independent
Requires-Python: >=3.6
License-File: LICENSE
Requires-Dist: numpy
Requires-Dist: pandas
